ladderinfo/__init__.py
ladderinfo/app.py
ladderinfo/static/images/allin_official.png
ladderinfo/static/images/bronze.png
ladderinfo/static/images/diamond.png
ladderinfo/static/images/discord-face.png
ladderinfo/static/images/gold.png
ladderinfo/static/images/grandmaster.png
ladderinfo/static/images/master.png
ladderinfo/static/images/platinum.png
ladderinfo/static/images/silver.png
ladderinfo/static/styles/main.css
ladderinfo/templates/root.html.j2
ladderinfo-0.0.3.dist-info/METADATA
ladderinfo-0.0.3.dist-info/RECORD
ladderinfo-0.0.3.dist-info/WHEEL
ladderinfo-0.0.3.dist-info/top_level.txt
